pyrace/__init__.py
pyrace/setting.py
pyrace/data/car_img.png
pyrace/data/car_img2.png
pyrace/data/map_1.jpg
pyrace/data/map_2.jpg
pyrace/data/map_3.jpg
pyrace/data/marker_img.png
pyrace/model/__init__.py
pyrace/model/camera.py
pyrace/model/car.py
pyrace/model/modelregistery.py
pyrace/model/space.py
pyrace/vue/__init__.py
pyrace/vue/mapregistery.py
pyrace-0.0.14.dist-info/LICENSE
pyrace-0.0.14.dist-info/METADATA
pyrace-0.0.14.dist-info/WHEEL
pyrace-0.0.14.dist-info/top_level.txt
pyrace-0.0.14.dist-info/RECORD
