Metadata-Version: 2.1
Name: pyrace
Version: 0.0.14
Summary: This package provides an environment to practice different types of reingorcement learning models.
Home-page: https://github.com/CedricJouan/pyrace
Author: Cedric Jouan
Author-email: cedric.jouan@ibm.com
License: UNKNOWN
Platform: UNKNOWN
Classifier: Programming Language :: Python :: 3
Classifier: License :: OSI Approved :: MIT License
Classifier: Operating System :: OS Independent
Requires-Python: >=3.6
Requires-Dist: numpy
Requires-Dist: matplotlib
Requires-Dist: pprint
Requires-Dist: pillow
